call_to_change/__init__.py
call_to_change/interceptor.py
call_to_change-0.8.6.dist-info/METADATA
call_to_change-0.8.6.dist-info/WHEEL
call_to_change-0.8.6.dist-info/top_level.txt
call_to_change-0.8.6.dist-info/RECORD
