Metadata-Version: 2.1
Name: call-to-change
Version: 0.8.6
Requires-Dist: openai
Requires-Dist: requests
